newapi_mcp/__init__.py
newapi_mcp/__main__.py
newapi_mcp/channels.py
newapi_mcp/client.py
newapi_mcp/config.py
newapi_mcp/logs.py
newapi_mcp/model_search.py
newapi_mcp/models.py
newapi_mcp/models_mgmt.py
newapi_mcp/pricing.py
newapi_mcp/server.py
newapi_mcp/token_management.py
newapi_mcp/tokens.py
newapi_mcp/tools_registry.py
newapi_mcp/users.py
newapi_mcp/validators.py
newapi_mcp-0.1.0.dist-info/METADATA
newapi_mcp-0.1.0.dist-info/WHEEL
newapi_mcp-0.1.0.dist-info/entry_points.txt
newapi_mcp-0.1.0.dist-info/licenses/LICENSE
newapi_mcp-0.1.0.dist-info/RECORD
